{
  "generatedAt": "2026-03-29T13:59:40.626Z",
  "rebuild": false,
  "distRoot": "src/apps/astro/dist",
  "checks": [
    {
      "entry": "es",
      "distCount": 33,
      "repoCount": 33,
      "missingInRepo": [],
      "extraInRepo": [],
      "changed": []
    },
    {
      "entry": "en",
      "distCount": 24,
      "repoCount": 24,
      "missingInRepo": [],
      "extraInRepo": [],
      "changed": []
    },
    {
      "entry": "_astro",
      "distCount": 8,
      "repoCount": 8,
      "missingInRepo": [],
      "extraInRepo": [],
      "changed": []
    }
  ],
  "passed": true,
  "driftCount": 0
}
